fakeopenai/__init__.py
fakeopenai/api.py
fakeopenai-0.3.dist-info/METADATA
fakeopenai-0.3.dist-info/WHEEL
fakeopenai-0.3.dist-info/top_level.txt
fakeopenai-0.3.dist-info/RECORD
